sqlsorcery/__init__.py
sqlsorcery-0.1.6.dist-info/LICENSE
sqlsorcery-0.1.6.dist-info/METADATA
sqlsorcery-0.1.6.dist-info/WHEEL
sqlsorcery-0.1.6.dist-info/top_level.txt
sqlsorcery-0.1.6.dist-info/RECORD
