Metadata-Version: 2.1
Name: sqlsorcery
Version: 0.1.6
Summary: Dead simple wrapper for pandas and sqlalchemy
Home-page: http://github.com/dchess/sqlsorcery
Author: dchess
Author-email: dc.hess@gmail.com
License: MIT
Platform: UNKNOWN
Requires-Dist: pandas
Requires-Dist: sqlalchemy
Provides-Extra: mssql
Requires-Dist: pyodbc ; extra == 'mssql'
Provides-Extra: mysql
Requires-Dist: PyMySQL ; extra == 'mysql'
Provides-Extra: oracle
Requires-Dist: cx-Oracle ; extra == 'oracle'
Provides-Extra: postgres
Requires-Dist: psycopg2-binary ; extra == 'postgres'
